test/__init__.py
test/test_account.py
test/test_account_response.py
test/test_account_response_result.py
test/test_amount.py
test/test_auth_api.py
test/test_balances_response.py
test/test_ban_response.py
test/test_bank_api.py
test/test_base_quote_response.py
test/test_block_api.py
test/test_block_response.py
test/test_block_response_header.py
test/test_block_response_header_version.py
test/test_block_response_id.py
test/test_block_response_id_parts.py
test/test_block_tx.py
test/test_block_tx_result.py
test/test_borrower.py
test/test_borrower_response.py
test/test_borrowers_api.py
test/test_borrowers_response.py
test/test_chain_height.py
test/test_clout_api.py
test/test_coin.py
test/test_constants_response.py
test/test_derived_pool.py
test/test_derived_pool_response.py
test/test_derived_pools_response.py
test/test_export_api.py
test/test_export_response.py
test/test_health_api.py
test/test_inbound_address.py
test/test_inbound_addresses_response.py
test/test_inbound_confirmation_counted_stage.py
test/test_inbound_finalised_stage.py
test/test_inbound_observed_stage.py
test/test_inline_response200.py
test/test_invariant_response.py
test/test_invariants_api.py
test/test_invariants_response.py
test/test_keygen.py
test/test_keygen_block.py
test/test_keygen_metric.py
test/test_keygen_metrics_response.py
test/test_keygen_response.py
test/test_keysign_info.py
test/test_keysign_metrics.py
test/test_keysign_response.py
test/test_last_block.py
test/test_last_block_response.py
test/test_liquidity_provider.py
test/test_liquidity_provider_response.py
test/test_liquidity_provider_summary.py
test/test_liquidity_providers_api.py
test/test_liquidity_providers_response.py
test/test_metrics_response.py
test/test_mimir_api.py
test/test_mimir_nodes_response.py
test/test_mimir_response.py
test/test_mimir_vote.py
test/test_msg_swap.py
test/test_network_api.py
test/test_network_response.py
test/test_node.py
test/test_node_bond_provider.py
test/test_node_bond_providers.py
xchainpy2_thornode-3.3.0.dist-info/LICENSE
xchainpy2_thornode-3.3.0.dist-info/METADATA
xchainpy2_thornode-3.3.0.dist-info/WHEEL
xchainpy2_thornode-3.3.0.dist-info/top_level.txt
xchainpy2_thornode-3.3.0.dist-info/RECORD
