Metadata-Version: 2.2
Name: xchainpy2-thornode
Version: 3.3.0
Summary: Thornode API
Home-page: 
Author-email: devs@thorchain.org
Keywords: Swagger,Thornode API
License-File: LICENSE
Requires-Dist: urllib3>=1.15
Requires-Dist: six>=1.10
Requires-Dist: certifi
Requires-Dist: python-dateutil
Requires-Dist: aiohttp
Dynamic: author-email
Dynamic: description
Dynamic: description-content-type
Dynamic: keywords
Dynamic: requires-dist
Dynamic: summary
